openai_image_mcp/__init__.py
openai_image_mcp/conversation_builder.py
openai_image_mcp/file_organizer.py
openai_image_mcp/image_processor.py
openai_image_mcp/responses_client.py
openai_image_mcp/server.py
openai_image_mcp/session_manager.py
openai_image_mcp-0.2.1.dist-info/LICENSE
openai_image_mcp-0.2.1.dist-info/METADATA
openai_image_mcp-0.2.1.dist-info/WHEEL
openai_image_mcp-0.2.1.dist-info/entry_points.txt
openai_image_mcp-0.2.1.dist-info/RECORD
