Metadata-Version: 2.3
Name: openai-image-mcp
Version: 0.2.1
Summary: Session-based conversational image generation MCP server using OpenAI's advanced models
Keywords: openai,mcp,image-generation,ai,claude,conversational
Author: Laza Bogdan
Author-email: laza.bogdan@macro-net.ro
Requires-Python: >=3.10,<4.0
Classifier: Development Status :: 4 - Beta
Classifier: Intended Audience :: Developers
Classifier: License :: OSI Approved :: MIT License
Classifier: Programming Language :: Python :: 3
Classifier: Programming Language :: Python :: 3.10
Classifier: Programming Language :: Python :: 3.11
Classifier: Programming Language :: Python :: 3.12
Classifier: Programming Language :: Python :: 3.13
Classifier: Topic :: Scientific/Engineering :: Artificial Intelligence
Classifier: Topic :: Software Development :: Libraries :: Python Modules
Requires-Dist: httpx (>=0.27.0,<0.28.0)
Requires-Dist: mcp[cli] (>=1.0.0,<2.0.0)
Requires-Dist: openai (>=1.82.0)
Requires-Dist: pydantic (>=2.0.0,<3.0.0)
Requires-Dist: python-dotenv (>=1.0.0,<2.0.0)
Requires-Dist: requests (>=2.32.3,<3.0.0)
Project-URL: Homepage, https://github.com/aigentive/openai-image-mcp
Project-URL: Repository, https://github.com/aigentive/openai-image-mcp
